spring/__init__.py
zen_spring-1.0.0.dist-info/METADATA
zen_spring-1.0.0.dist-info/WHEEL
zen_spring-1.0.0.dist-info/top_level.txt
zen_spring-1.0.0.dist-info/RECORD
